mux4x1.v
module mux4x1 (
    input wire [3:0] data, // 4 data inputs
    input wire [1:0] sel,  // 2-bit select input
    output wire y          // Output
);
    assign y = (sel == 2'b00) ? data[0] :
               (sel == 2'b01) ? data[1] :
               (sel == 2'b10) ? data[2] : data[3];
endmodule

mux8x1.v
module mux8x1 (
    input wire [7:0] data,  // 8 data inputs
    input wire [2:0] sel,   // 3-bit select input
    output wire y           // Output
);

    wire y1, y2;  // Outputs from the two 4x1 MUXes

    // First 4x1 MUX for the lower 4 inputs (data[3:0])
    mux4x1 mux1 (
        .data(data[3:0]),
        .sel(sel[1:0]),
        .y(y1)
    );

    // Second 4x1 MUX for the higher 4 inputs (data[7:4])
    mux4x1 mux2 (
        .data(data[7:4]),
        .sel(sel[1:0]),
        .y(y2)
    );

    // 2x1 MUX to select between the outputs of the two 4x1 MUXes
    assign y = (sel[2] == 1'b0) ? y1 : y2;

endmodule

tb_mux8x1.v
module tb_mux8x1;

    reg [7:0] data;   // 8 data inputs
    reg [2:0] sel;    // 3-bit select input
    wire y;           // Output

    // Instantiate the 8x1 MUX
    mux8x1 uut (
        .data(data),
        .sel(sel),
        .y(y)
    );

    // Stimulus
    initial begin
        // Create waveform dump
        $dumpfile("dump.vcd");         // VCD output file
        $dumpvars(0, tb_mux8x1);       // Dump all signals in this module

        // Display the values of data, sel, and y
        $monitor("time = %0t, data = %b, sel = %b, y = %b", $time, data, sel, y);

        // Example pattern
        data = 8'b01010101;

        sel = 3'b000; #10;
        sel = 3'b001; #10;
        sel = 3'b010; #10;
        sel = 3'b011; #10;
        sel = 3'b100; #10;
        sel = 3'b101; #10;
        sel = 3'b110; #10;
        sel = 3'b111; #10;

        $finish;
    end

endmodule

dump.vcd
$date
	Thu Apr 17 12:15:06 2025
$end
$version
	Icarus Verilog
$end
$timescale
	1s
$end
$scope module tb_mux8x1 $end
$var wire 1 ! y $end
$var reg 8 " data [7:0] $end
$var reg 3 # sel [2:0] $end
$scope module uut $end
$var wire 8 $ data [7:0] $end
$var wire 3 % sel [2:0] $end
$var wire 1 & y2 $end
$var wire 1 ' y1 $end
$var wire 1 ! y $end
$scope module mux1 $end
$var wire 4 ( data [3:0] $end
$var wire 2 ) sel [1:0] $end
$var wire 1 ' y $end
$upscope $end
$scope module mux2 $end
$var wire 4 * data [3:0] $end
$var wire 2 + sel [1:0] $end
$var wire 1 & y $end
$upscope $end
$upscope $end
$upscope $end
$enddefinitions $end
$comment Show the parameter values. $end
$dumpall
$end
#0
$dumpvars
b0 +
b101 *
b0 )
b101 (
1'
1&
b0 %
b1010101 $
b0 #
b1010101 "
1!
$end
#10
0!
0'
0&
b1 )
b1 +
b1 #
b1 %
#20
1!
1'
1&
b10 )
b10 +
b10 #
b10 %
#30
0!
0'
0&
b11 )
b11 +
b11 #
b11 %
#40
1!
1'
1&
b0 )
b0 +
b100 #
b100 %
#50
0!
0'
0&
b1 )
b1 +
b101 #
b101 %
#60
1!
1'
1&
b10 )
b10 +
b110 #
b110 %
#70
0!
0'
0&
b11 )
b11 +
b111 #
b111 %
